decrypto/__init__.py
decrypto/src/__init__.py
decrypto/src/affine_cipher.py
decrypto/src/ascii_cipher.py
decrypto/src/atbash_cipher.py
decrypto/src/bacon_cipher.py
decrypto/src/base64_cipher.py
decrypto/src/binary_cipher.py
decrypto/src/caesar_cipher.py
decrypto/src/hexadecimal_cipher.py
decrypto/src/morse_code_cipher.py
decrypto/src/octal_cipher.py
decrypto/src/reverse_cipher.py
decrypto/src/roman_numeral_cipher.py
decrypto/src/rot13_cipher.py
decrypto/src/rsa_cipher.py
decrypto/src/scytale_cipher.py
decrypto/src/vigenere_cipher.py
tests/__init__.py
tests/test_affine_cipher.py
tests/test_ascii_cipher.py
tests/test_atbash_cipher.py
tests/test_bacon_cipher.py
tests/test_base64_cipher.py
tests/test_binary_cipher.py
tests/test_caesar_cipher.py
tests/test_hexadecimal_cipher.py
tests/test_octal_cipher.py
tests/test_reverse_cipher.py
tests/test_roman_numeral_cipher.py
tests/test_rot13_cipher.py
tests/test_vigenere_cipher.py
decrypto-1.1.1.dist-info/LICENSE
decrypto-1.1.1.dist-info/METADATA
decrypto-1.1.1.dist-info/WHEEL
decrypto-1.1.1.dist-info/top_level.txt
decrypto-1.1.1.dist-info/RECORD
