Metadata-Version: 2.1
Name: decrypto
Version: 1.1.1
Summary: Light Weight python package for encrption/decryption
Home-page: https://github.com/pyGuru123/Decrypto
Author: Prajjwal Pathak
Author-email: pyguru123@gmail.com
License: UNKNOWN
Platform: UNKNOWN
Classifier: Programming Language :: Python :: 3
Classifier: License :: OSI Approved :: MIT License
Classifier: Operating System :: OS Independent
Requires-Python: >=3.5
License-File: LICENSE
